{
"type": "FeatureCollection",
"name": "Whangarei_Kawakawa_LiDAR_2025 - Imagery_Centres",
"crs": { "type": "name", "properties": { "name": "urn:ogc:def:crs:OGC:1.3:CRS84" } },
"xy_coordinate_resolution": 1e-15,
"features": [
{ "type": "Feature", "properties": { "Project": "FPFA", "Proj_Name": "Whangarei_Kawakawa_LiDAR_2025", "Survey_Typ": "Imagery", "OrthoGSD_m": 10.0 }, "geometry": { "type": "Point", "coordinates": [ 174.245471038115937, -35.536460042117959 ] } }
]
}
